[
    {
        "id": 1,   
        "title": "Microsoft Xbox Series Standard",
        "desc" : "Consolas y VideoJuegos",
        "innerHeading": "Microsoft Xbox Series Standard",
        "price": 7608,
        "img" : "https://telegra.ph/file/d6c85059669fb6f2fadf1.png",
        "propiedad" : ["•Incluye control", "•Resolución de 2560 px x 1440 px.", "•Memoria RAM de 10GB","•Horas de diversión garantizada", 
        "•Cuenta con 1 cable hdmi, 1 cable de alimentación ca"]
    },
    {
        "id": 2,   
        "title": "Microsoft Xbox Series X 1TB Standard color negro",
        "desc" : "Consolas y VideoJuegos",
        "innerHeading": "Microsoft Xbox Series X 1TB Standard color negro",
        "price": 15340,
        "img" : "https://telegra.ph/file/1b3f27689ee97a7bea52c.png",
        "propiedad" : ["•Incluye control", "•Resolución de 2560 px x 1440 px.", "•Memoria RAM de 16GB","•Horas de diversión garantizada", 
        "•Cuenta con 1 cable hdmi, 1 cable de alimentación ca"]
    },
    {
        "id": 3,   
        "title": "Nintendo Switch OLED 64GB Standard color rojo neón, azul neón y negro",
        "desc" : "Consolas y VideoJuegos",
        "innerHeading": "Nintendo Switch OLED 64GB Standard color rojo neón, azul neón y negro",
        "price": 8788,
        "img" : "https://telegra.ph/file/ef54f49cdf99e17832c90.png",
        "propiedad" : ["•Incluye 2 controles", "•Resolución de 1920 px x 1080 px", "•Memoria RAM de 4GB","•Tiene pantalla táctil", 
        "•La duración de la batería es de 9h"]
    },
    {
        "id": 4,   
        "title": "Nintendo Switch Version Animal Crossing New Horizons",
        "desc" : "Consolas y VideoJuegos",
        "innerHeading": "Nintendo Switch Version Animal Crossing New Horizons",
        "price": 8849,
        "img" : "https://telegra.ph/file/92817eca4dcf08df97458.png",
        "propiedad" : ["•Pantalla: LCD de 6.2 pulgadas", "•Resolución de 1280 x 720", "•Memoria RAM de 32GB","•CPU / GPU: procesador NVIDIA Tegra", 
        "•Batería interna: 4310 mAh"]
    },
    {
        "id": 5,   
        "title": "Nintendo Switch New Version 32gb Joy-con",
        "desc" : "Consolas y VideoJuegos",
        "innerHeading": "Nintendo Switch Version Animal Crossing New Horizons",
        "price": 7659,
        "img" : "https://telegra.ph/file/57b225db7b36fd1a02b60.png",
        "propiedad" : ["•Incluye 2 controles", "•Resolución de 11280 x 720", "•Memoria RAM de 32GB","•CPU / GPU: procesador NVIDIA Tegra", 
        "•Batería interna: 4310 mAh"]
    },
    {
        "id": 6,   
        "title": "Nintendo Switch Version 2 Mario Kart 8 Deluxe Neon",
        "desc" : "Consolas y VideoJuegos",
        "innerHeading": "Nintendo Switch Version Animal Crossing New Horizons",
        "price": 9999,
        "img" : "https://telegra.ph/file/b08d9276f4173af285ea5.png",
        "propiedad" : ["•Pantalla: LCD de 6.2 pulgadas", "•Resolución de 1280 x 720", "•Memoria RAM de 32GB","•CPU / GPU: procesador NVIDIA Tegra", 
        "•Batería interna: 4310 mAh"]
    },
    {
        "id": 7,   
        "title": "Moto G60 Dual SIM 128 GB plata 6 GB RAM",
        "desc" : "Celulares y Telefonía",
        "innerHeading": "Moto G60 Dual SIM 128 GB plata 6 GB RAM",
        "price": 4879,
        "img" : "https://telegra.ph/file/b41e9f07f8dcc54fade01.png",
        "propiedad" : ["•Pantalla IPS de 6.8", "•Tiene 3 cámaras traseras de 108Mpx/8Mpx/2Mpx", "•Procesador Snapdragon 732G Octa-Core de 2.3GHz con 6GB de RAM",
        "•Batería de 6000mAh", "•Memoria interna de 128GB"]
    },
    {
        "id": 8,   
        "title": "Xiaomi Redmi 9A Dual SIM 64 GB azul celeste 4 GB RAM",
        "desc" : "Celulares y Telefonía",
        "innerHeading": "Xiaomi Redmi 9A Dual SIM 64 GB azul celeste 4 GB RAM",
        "price": 3123,
        "img" : "https://telegra.ph/file/7fb92ced82a8417a2dc8d.png",
        "propiedad" : ["•Pantalla IPS de 6.53", "•Cámara delantera de 5Mpx", "•Procesador MediaTek MT6762G Helio G25 Octa-Core de 2GHz con 4GB de RAM",
        "•Batería de 5000mAh", "•Memoria interna de 64GB"]
    },
    {
        "id": 9,   
        "title": "Audífonos In-ear Inalámbricos Samsung Galaxy Buds Pro Blanco",
        "desc" : "Celulares y Telefonía",
        "innerHeading": "Audífonos In-ear Inalámbricos Samsung Galaxy Buds",
        "price": 2999,
        "img" : "https://telegra.ph/file/67a45730373188a5f53ab.png",
        "propiedad" : ["•Cuenta con tecnología True Wireless", "•La batería dura 5h", "•Asistente de voz integrado: Bixby",
        "•Con estuche de carga inalámbrica", "•Su clasificación IP es IPX7"]
    },
    {
        "id": 10,   
        "title": "Oppo A54 Dual SIM 128 GB azul 4 GB RAM",
        "desc" : "Celulares y Telefonía",
        "innerHeading": "Oppo A54 Dual SIM 128 GB azul 4 GB RAM",
        "price": 4849,
        "img" : "https://telegra.ph/file/dd64cf88a55db12c33f31.png",
        "propiedad" : ["•Pantalla IPS de 6.51", "•Tiene 3 cámaras traseras de 13Mpx/2Mpx/2Mpx", "•Cámara delantera de 16Mpx",
        "•Batería de 5000mAh", "•Memoria interna de 128GB"]
    },
    {
        "id": 11,   
        "title": "Xiaomi Pocophone Poco X4 Pro 5G Dual SIM 256 GB",
        "desc" : "Celulares y Telefonía",
        "innerHeading": "Xiaomi Pocophone Poco X4 Pro 5G Dual SIM 256 GB poco yellow 8 GB RAM",
        "price": 7259,
        "img" : "https://telegra.ph/file/a7a682b1bf7d98aab1e32.png",
        "propiedad" : ["•Pantalla IPS de 6.51", "•Tiene 3 cámaras traseras de 13Mpx/2Mpx/2Mpx", "•Cámara delantera de 16Mpx",
        "•Batería de 5000mAh", "•Memoria interna de 128GB"]
    },
    {
        "id": 12,   
        "title": "Honor X7 128gb Dual Sim 4gb Ram 48mpx Snapdragon 680",
        "desc" : "Celulares y Telefonía",
        "innerHeading": "Honor X7 128gb Dual Sim 4gb Ram 48mpx Snapdragon 680",
        "price": 4599,
        "img" : "https://telegra.ph/file/c533d98c5853ff7c3c8d4.png",
        "propiedad" : ["•Pantalla TFT de 6.74 pulgadas", "•Cámara delantera de 8Mpx", "•Procesador Snapdragon 680 Octa-Core de 2.4GHz con 4GB de RAM",
        "•Batería de 5000mAh", "•Memoria interna de 128GB"]
    },
    {
        "id": 13,   
        "title": "Xiaomi Mi Smart Band 7 1.62",
        "desc" : "Joyas y Relojes",
        "innerHeading": "Xiaomi Mi Smart Band 7 1.62 caja negra, malla negra",
        "price": 1110,
        "img" : "https://telegra.ph/file/4bc7051f7cc0730fbb1ae.png",
        "propiedad" : ["•Pantalla AMOLED de 1.62", "•Resiste hasta 50m bajo el agua", "•Batería de 7 días de duración",
        "•Conectividad por bluetooth", "•Sensores incluidos: pulsioxímetro, podómetro, sensor hr, acelerómetro, giroscopio"]
    },
    {
        "id": 14,   
        "title": "Smartwatch Amazfit Basic Bip U 1.43",
        "desc" : "Joyas y Relojes",
        "innerHeading": "Smartwatch Amazfit Basic Bip U 1.43 caja de policarbonato black",
        "price": 1399,
        "img" : "https://telegra.ph/file/93043b8dafb7017e581cc.png",
        "propiedad" : ["•Pantalla táctil LCD TFT de 1.43", "•Resiste hasta 50m bajo el agua", "•Batería de 9 días de duración",
        "•Conectividad por bluetooth", "•Correa intercambiable por otros colores, no incluidos en el producto"]
    },
    {
        "id": 15,   
        "title": "Smartwatch Amazfit Sport T-Rex Pro 1.3 caja 47.7mm",
        "desc" : "Joyas y Relojes",
        "innerHeading": "Smartwatch Amazfit Sport T-Rex Pro 1.3 caja 47.7mm",
        "price": 3599,
        "img" : "https://telegra.ph/file/145ade7e62f61b561b6b6.png",
        "propiedad" : ["•Pantalla táctil AMOLED de 1.3", "•Apto para descarga de aplicaciones", "•Resiste hasta 100m bajo el agua",
        "•Con GPS integrado", "•Batería de 18 días de duración."]
    },
    {
        "id": 16,   
        "title": "Smartwatch Amazfit GTS 3 1.75 caja de aleación de aluminio ivory",
        "desc" : "Joyas y Relojes",
        "innerHeading": "Smartwatch Amazfit GTS 3 1.75 caja de aleación de aluminio ivory white",
        "price": 3599,
        "img" : "https://telegra.ph/file/145ade7e62f61b561b6b6.png",
        "propiedad" : ["•Pantalla táctil AMOLED de 1.3", "•Apto para descarga de aplicaciones", "•Resiste hasta 50m bajo el agua",
        "•Con GPS integrado", "•Batería de 12 días de duración."]
    },
    {
        "id": 17,   
        "title": "Smartwatch Amazfit Basic Bip U Pro 1.43",
        "desc" : "Joyas y Relojes",
        "innerHeading": "Smartwatch Amazfit Basic Bip U Pro 1.43",
        "price": 3599,
        "img" : "https://telegra.ph/file/145ade7e62f61b561b6b6.png",
        "propiedad" : ["•Pantalla táctil LCD TFT de 1.43", "•Resiste hasta 50m bajo el agua", "•Con GPS integrado",
        "•Con GPS integrado", "•Batería de 12 días de duración."]
    },
    {
        "id": 18,   
        "title": "Bocina Philips EverPlay BT6900 portátil con bluetooth negra",
        "desc" : "Audio y video",
        "innerHeading": "Bocina Philips EverPlay BT6900 portátil con bluetooth negra",
        "price": 1109,
        "img" : "https://telegra.ph/file/6fa4a4ac62f048fb830cc.png",
        "propiedad" : ["•Es manos libres", "•Es a prueba de el agua", "•Apta para uso en exteriores",
        "•Potencia de 10W", "•Conector de entrada: Auxiliar"]
    },
    {
        "id": 19,   
        "title": "Gravity Bocina Portatil Con Luz Led 2x8 80w Gravity-8 Negro",
        "desc" : "Audio y video",
        "innerHeading": "Gravity Bocina Portatil Con Luz Led 2x8 80w Gravity-8 Negro",
        "price": 6499,
        "img" : "https://telegra.ph/file/fb01c00eb3cc69ac291da.png",
        "propiedad" : ["•Tipos de parlante: Woofer", "•Es a prueba de el agua", "•Con Bluetooth: Sí",
        "•Potencia de 10W", "•Conector de entrada: Auxiliar"]
    },
    {
        "id": 20,   
        "title": "Amazon Echo Show 8 Pantalla Inteligente Hd Negro",
        "desc" : "Audio y video",
        "innerHeading": "Amazon Echo Show 8 Pantalla Inteligente Hd Negro",
        "price": 20000,
        "img" : "https://telegra.ph/file/a1ffd1e2eab585370c272.png",
        "propiedad" : ["•Con sistema de audio multi-room: Sí", "•Con cámara: Sí", "•Con Bluetooth: Sí",
        "•Con display digital: Sí", "•Asistentes virtuales: Alexa"]
    },
    {
        "id": 21,   
        "title": "Amazon Echo Show 8 Pantalla Inteligente Hd Negro",
        "desc" : "Audio y video",
        "innerHeading": "Amazon Echo Show 8 Pantalla Inteligente Hd Negro",
        "price": 20000,
        "img" : "https://telegra.ph/file/a1ffd1e2eab585370c272.png",
        "propiedad" : ["•Con sistema de audio multi-room: Sí", "•Con cámara: Sí", "•Con Bluetooth: Sí",
        "•Con display digital: Sí", "•Asistentes virtuales: Alexa"]
    },
    {
        "id": 22,   
        "title": "Gravity Bocina Portatil Con Luz Led 2x10 100w Gravity-10 Ne",
        "desc" : "Audio y video",
        "innerHeading": "Gravity Bocina Portatil Con Luz Led 2x10 100w Gravity-10 Ne",
        "price": 6499,
        "img" : "https://telegra.ph/file/cb8862363b9d6255a46e1.png",
        "propiedad" : ["•Tipos de parlante: Woofer", "•Es a prueba de el agua", "•Con Bluetooth: Sí",
        "•Potencia de 10W", "•Conector de entrada: Auxiliar"]
    },
    {
        "id": 23,   
        "title": "Amazon Echo Show 8 Pantalla Inteligente Hd Blanca",
        "desc" : "Audio y video",
        "innerHeading": "Amazon Echo Show 8 Pantalla Inteligente Hd Blanca",
        "price": 20000,
        "img" : "https://telegra.ph/file/7ad8c08d41d56c01f8060.png",
        "propiedad" : ["•Con sistema de audio multi-room: Sí", "•Con cámara: Sí", "•Con Bluetooth: Sí",
        "•Con display digital: Sí", "•Asistentes virtuales: Alexa"]
    },
    {
        "id": 24,   
        "title": "Proyector Portátil Mundial 2022 Blanco",
        "desc" : "Audio y video",
        "innerHeading": "Proyector Portátil Mundial 2022 Blanco",
        "price": 1799,
        "img" : "https://telegra.ph/file/3a7a7f96e30abd89f5f60.png",
        "propiedad" : ["•Brillo de la imagen: 1200 lm", "•Tamaño de la imagen: 800 X 480 DPI", "•Conexiones de entrada: AV",
        "•Con display digital: Sí", "•Fuentes de luz: LED"]
    },
    {
        "id": 25,   
        "title": "Proyector Portátil Mundial 2022 Rojo",
        "desc" : "Audio y video",
        "innerHeading": "Proyector Portátil Mundial 2022 Rojo",
        "price": 1799,
        "img" : "https://telegra.ph/file/3a7a7f96e30abd89f5f60.png",
        "propiedad" : ["•Brillo de la imagen: 1200 lm", "•Tamaño de la imagen: 800 X 480 DPI", "•Conexiones de entrada: AV",
        "•Con display digital: Sí", "•Fuentes de luz: LED"]
    },
    {
        "id": 26,   
        "title": "Proyector Portátil Mundial 2022 Azul",
        "desc" : "Audio y video",
        "innerHeading": "Proyector Portátil Mundial 2022 Azul",
        "price": 1799,
        "img" : "https://telegra.ph/file/3a7a7f96e30abd89f5f60.png",
        "propiedad" : ["•Brillo de la imagen: 1200 lm", "•Tamaño de la imagen: 800 X 480 DPI", "•Conexiones de entrada: AV",
        "•Con display digital: Sí", "•Fuentes de luz: LED"]
    },
    {
        "id": 27,   
        "title": "Proyector Portátil Mundial 2022 Amarillo",
        "desc" : "Audio y video",
        "innerHeading": "Proyector Portátil Mundial 2022 Amarillo",
        "price": 1799,
        "img" : "https://telegra.ph/file/3a7a7f96e30abd89f5f60.png",
        "propiedad" : ["•Brillo de la imagen: 1200 lm", "•Tamaño de la imagen: 800 X 480 DPI", "•Conexiones de entrada: AV",
        "•Con display digital: Sí", "•Fuentes de luz: LED"]
    },
    {
        "id": 28,   
        "title": "Samsung Projector Inteligente Blanco Sp-lsp3bla",
        "desc" : "Audio y video",
        "innerHeading": "Samsung Projector Inteligente Blanco Sp-lsp3bla",
        "price": 15999,
        "img" : "https://telegra.ph/file/1ce953231527c94f1b5fb.png",
        "propiedad" : ["•Brillo de la imagen: 550 lm", "•Tamaño de la imagen: 30 a 100", "•Con Wi-Fi: Sí",
        "•Con display digital: Sí", "•Fuentes de luz: LED"]
    },
    {
        "id": 29,   
        "title": "Amazon Fire TV Stick Lite de voz Full HD 8GB negro",
        "desc" : "Audio y video",
        "innerHeading": "Amazon Fire TV Stick Lite de voz Full HD 8GB negro",
        "price": 891,
        "img" : "https://telegra.ph/file/ab98d0bfb24e601b76780.png",
        "propiedad" : ["•Brillo de la imagen: 550 lm", "•Tamaño de la imagen: 30 a 100", "•Con Wi-Fi: Sí",
        "•Con display digital: Sí", "•Fuentes de luz: LED"]
    },
    {
        "id": 30,   
        "title": "Google chromecast 3 negro",
        "desc" : "Audio y video",
        "innerHeading": "Google chromecast 3 negro",
        "price": 966,
        "img" : "https://telegra.ph/file/b7c55ba4445cf02778f41.png",
        "propiedad" : ["•Capacidad de almacenamiento: 512 MB", "•Resolución máxima de video: 4K", "•Con Wi-Fi: Sí",
        "•Con display digital: Sí", "•Fuentes de luz: LED"]
    },
    {
        "id": 31,   
        "title": "Samsung Business Tv Led Display 50 125.7cm Be50t-h Db01",
        "desc" : "Audio y video",
        "innerHeading": "Samsung Business Tv Led Display 50 125.7cm Be50t-h Db01",
        "price": 13949,
        "img" : "https://telegra.ph/file/6d67cc43c5e0479153b63.png",
        "propiedad" : ["•Tipo de pantalla: LED", "•Resolución máxima de video: 4K", "•Con Wi-Fi: Sí",
        "•Es smart: Sí", "•Fuentes de luz: LED"]
    },
    {
        "id": 32,   
        "title": "Samsung Pro Tv Led Display 50   125.7cm Be50t-h Ab02",
        "desc" : "Audio y video",
        "innerHeading": "Samsung Pro Tv Led Display 50   125.7cm Be50t-h Ab02",
        "price": 13949,
        "img" : "https://telegra.ph/file/6d67cc43c5e0479153b63.png",
        "propiedad" : ["•Tipo de pantalla: LED", "•Resolución máxima de video: 4K", "•Con Wi-Fi: Sí",
        "•Es smart: Sí", "•Fuentes de luz: LED"]
    },
    {
        "id": 33,   
        "title": "Xiaomi Protector De Hélices Mi Mini Drone",
        "desc" : "Audio y video",
        "innerHeading": "Xiaomi Protector De Hélices Mi Mini Drone",
        "price": 399,
        "img" : "https://telegra.ph/file/dc3775460d6b8d79bab0c.png",
        "propiedad" : ["•Peso del paquete: 1 kg", "•Medidas: 5.6 x 5.3 x 2.6 cm", "•Color: Blanco",
        "•Modelo: PROTMIDRONEMINI", "•Meses de garantía: 3"]
    },
    {
        "id": 34,   
        "title": "Tablet Samsung Galaxy A7 Lite SM-T225",
        "desc" : "Audio y video",
        "innerHeading": "Tablet Samsung Galaxy A7 Lite SM-T225",
        "price": 4379,
        "img" : "https://telegra.ph/file/6d67cc43c5e0479153b63.png",
        "propiedad" : ["•Sistema operativo: Android 11.0.", "•Con procesador 2 Quad-Core Cortex-A53 de 2.3GHz", "•Resolución de pantalla de 1340px x 800px",
        "•Con lector micro-SD, micro-SDxc", "•Memoria interna expandible hasta 1 TB con fuente externa"]
    },
    {
        "id": 35,   
        "title": "Hp 14-dk1008 Amd Athlon Silver 3050u",
        "desc" : "Computación",
        "innerHeading": "Hp 14-dk1008 Amd Athlon Silver 3050u",
        "price": 9999,
        "img" : "https://telegra.ph/file/3cc1c4d717671b1ca43b0.png",
        "propiedad" : ["•Memoria RAM: 4 GB", "•Tamaño de la pantalla: 14", "•Sistema Operativo: Windows 10",
        "•Memoria interna: SSD M.2 de 128 GB", "•Procesador: AMD Athlon 3050U 2.3 GHz"]
    },
    {
        "id": 36,   
        "title": "Huawei Mediapad T3 10 3gb 32gb Gris",
        "desc" : "Computación",
        "innerHeading": "Huawei Mediapad T3 10 3gb 32gb Gris",
        "price": 2932,
        "img" : "https://telegra.ph/file/e205bc4d3942edcd77414.png",
        "propiedad" : ["•Memoria RAM: 3 GB", "•Tamaño de la pantalla: 9.6", "•Capacidad: 32 GB",
        "•Cámara frontal: 5 Mpx", "•Cámaras traseras: 2 Mpx"]
    },
    {
        "id": 37,   
        "title": "Alcatel 3t 10 Smart 4g 2gb 32gb Negro Teclado + Flip Cover",
        "desc" : "Computación",
        "innerHeading": "Alcatel 3t 10 Smart 4g 2gb 32gb Negro Teclado + Flip Cover",
        "price": 4499,
        "img" : "https://telegra.ph/file/8d5772d8bddd881a542e8.png",
        "propiedad" : ["•Memoria RAM: 2 GB", "•Tamaño de la pantalla: 10", "•Capacidad: 32 GB",
        "•Cámara frontal: 2 Mpx", "•Cámaras traseras: 2 Mpx"]
    },
    {
        "id": 38,   
        "title": "Xiaomi Mi Lámpara De Escritorio Inteligente Pro Blanco",
        "desc" : "Hogar, muebles y jardín",
        "innerHeading": "Xiaomi Mi Lámpara De Escritorio Inteligente Pro Blanco",
        "price": 1999,
        "img" : "https://telegra.ph/file/2993f727e60b69ee69275.png",
        "propiedad" : ["•Memoria RAM: 2 GB", "•Tamaño de la pantalla: 10", "•Capacidad: 32 GB",
        "•Cámara frontal: 2 Mpx", "•Cámaras traseras: 2 Mpx"]
    },
    {
        "id": 39,   
        "title": "Xiaomi Yeelight Lightstrip Plus Blanco",
        "desc" : "Hogar, muebles y jardín",
        "innerHeading": "Xiaomi Yeelight Lightstrip Plus Blanco",
        "price": 899,
        "img" : "https://telegra.ph/file/7c4e92902c22672b33d24.png",
        "propiedad" : ["•Incluye controlador de color: Sí", "•Incluye fuente de alimentación: Sí", "•Color De La Luz:RGB",
        "•Largo: 1M", "•Voltaje: 110V"]
    },
    {
        "id": 40,   
        "title": "Xiaomi Mi Robot Vacuum-mop Brush Stzs01zhm",
        "desc" : "Hogar, muebles y jardín",
        "innerHeading": "Xiaomi Mi Robot Vacuum-mop Brush Stzs01zhm",
        "price": 399,
        "img" : "https://telegra.ph/file/2d6fae096ffdec16cf7e4.png",
        "propiedad" : ["•Modelo: STZS01ZHM", "•Unidades por envase: 1", "•Color De La Luz:RGB",
        "•Marca: Xiaomi", "•Voltaje: 110V"]
    },
    {
        "id": 41,   
        "title": "Xiaomi Mi Handheld Vacuum Cleaner Blanco 1c",
        "desc" : "Hogar, muebles y jardín",
        "innerHeading": "Xiaomi Mi Handheld Vacuum Cleaner Blanco 1c",
        "price": 7199,
        "img" : "https://telegra.ph/file/26e7295f7ef89f0e8fe69.png",
        "propiedad" : ["•Modelo: STZS01ZHM", "•Poder 25,2 V", "•Potencia nominal 400 vatios",
        "•Marca: Xiaomi", "•Tensión nominal 25,2 V"]
    },
    {
        "id": 42,   
        "title": "Xiaomi Mi Robot Vacuum Cepillo Gris",
        "desc" : "Hogar, muebles y jardín",
        "innerHeading": "Xiaomi Mi Robot Vacuum Cepillo Gris",
        "price": 399,
        "img" : "https://telegra.ph/file/26e7295f7ef89f0e8fe69.png",
        "propiedad" : ["•Medidas: 3 x 9 x 25 cm", "•Meses de garantía: 3", "•Nombre de color: Gris",
        "•Marca: Xiaomi", "•Modelo: XMIRBTCEP"]
    },
    {
        "id": 43,   
        "title": "Xiaomi Mi Rasuradora Electrica S500 Negro",
        "desc" : "Belleza y cuidado personal",
        "innerHeading": "Xiaomi Mi Rasuradora Electrica S500 Negro",
        "price": 1199,
        "img" : "https://telegra.ph/file/67825ccb4e63e7bd0f4b2.png",
        "propiedad" : ["•Afeitado en seco o mojado", "•Superficie antihuellas PPG", "•Tecnología de afeitado flotante 360°",
        "•Marca: Xiaomi", "•Autonomía de 60 minutos"]
    },
    {
        "id": 44,   
        "title": "Xiaomi Mi Rasuradora Eléctrica S500 Repuesto Head",
        "desc" : "Belleza y cuidado personal",
        "innerHeading": "Xiaomi Mi Rasuradora Eléctrica S500 Repuesto Head",
        "price": 309,
        "img" : "https://telegra.ph/file/38523dd16ecc38ef09788.png",
        "propiedad" : ["•Afeitado en seco o mojado", "•Es inalámbrica: Sí", "•Tecnología de afeitado flotante 360°",
        "•Marca: Xiaomi", "•Autonomía de 60 minutos"]
    }

    
    


    
]